[   



{
           "league": "🏆 Laliga",
            "date": "April 8",
            "time": "live",
            "himg": "https://images.fotmob.com/image_resources/logo/teamlogo/8558_small.png",
            "aimg": "https://images.fotmob.com/image_resources/logo/teamlogo/8315_small.png",
            "teams" : "Espanyol Vs Athletic Club",
            "hteam" : "Espanyol",
            "ateam" : "Athletic Club",
            "hotmat":"no",
           "link":[
  
                                         
{
                    "type": "SD 2",
                "livelink":"https://e53dc1c060e87be95abb5a524b1752f1.livehwc3.cn/pull06.scstream.net/live/stream-197901_lsd.m3u8?sub_m3u8=true&user_session_id=950025df6d50d934ec1f96c1cd8bd1e2&edge_slice=true&auth_key=1680983337-0-0-89ebb08ce14ba7d6e651f2841c3f3a90"
         
                },
{
                    "type": "HD",
                "livelink":"https://e53dc1c060e87be95abb5a524b1752f1.livehwc3.cn/pull06.scstream.net/live/stream-197901_lhd.m3u8?sub_m3u8=true&auth_key=1680983337-0-0-65563cf8abcec92c6fd12a20da5b3465&edge_slice=true&user_session_id=0ded9577b8893d35485209f0bc09c8fa"
         
                
                }
                
            ]
},
{
           "league": "🏆 Serie A",
            "date": "April 8",
            "time": "live",
            "himg": "https://images.fotmob.com/image_resources/logo/teamlogo/8524_small.png",
            "aimg": "https://images.fotmob.com/image_resources/logo/teamlogo/9857_small.png",
            "teams" : "Atalanta Vs Bologna",
            "hteam" : "Atalanta",
            "ateam" : "Bologna",
            "hotmat":"no",
            "link":[
  
                                         
{
                    "type": "SD 2",
                "livelink":"https://651e411010b7d90167dfb5b08bc317d5.livehwc3.cn/pull.juqihuo.com/live/stream-789220_lsd.m3u8?auth_key=1680981405-0-0-90686b7799ffad69ef010473d5271eaf&user_session_id=7b44675f9cc468e13e311d1c84d3aa74&edge_slice=true&sub_m3u8=true"
         
                },
{
                    "type": "HD",
                "livelink":"https://sports01.livnvess.com/live/stream-106737.m3u8?txSecret=63753c3aa5d1c2b0925e384cd991de47&txTime=6431c5a1"
         
                },
{
                    "type": "HD 2",
                "livelink":"https://651e411010b7d90167dfb5b08bc317d5.livehwc3.cn/pull.juqihuo.com/live/stream-789220_lhd.m3u8?auth_key=1680981405-0-0-7e3c59cd299044042ae150712bf8a57c&sub_m3u8=true&user_session_id=ee733e1dfa88c85b26069998ff9033b2&edge_slice=true"
                }
                
            ]
},
{
           "league": "🏆 Serie A",
            "date": "April 8",
            "time": "live",
            "himg": "https://images.fotmob.com/image_resources/logo/teamlogo/9882_small.png",
            "aimg": "https://images.fotmob.com/image_resources/logo/teamlogo/7801_small.png",
            "teams" : "Sampdoria Vs Cremonese",
            "hteam" : "Sampdoria",
            "ateam" : "Cremonese",
            "hotmat":"no",
            "link":[
  
                                        
{
                    "type": "SD 2",
                "livelink":"https://651e411010b7d90167dfb5b08bc317d5.livehwc3.cn/pull.juqihuo.com/live/stream-459156_lsd.m3u8?sub_m3u8=true&user_session_id=de8994fa76aaf395d647e989b4e953fe&auth_key=1680981345-0-0-c5df6908123501b372804bf2b684ab12&edge_slice=true"
         
                },

{
                    "type": "HD 2",
                "livelink":"https://651e411010b7d90167dfb5b08bc317d5.livehwc3.cn/pull.juqihuo.com/live/stream-459156_lhd.m3u8?sub_m3u8=true&auth_key=1680981345-0-0-cbd4a1c086ab9880f626f373d0479980&edge_slice=true&user_session_id=32770f41e99926cd21185a58c003be75"
                }
                
            ]
},
{
           "league": "🏆 Ligue 1",
            "date": "April 8",
            "time": "live",
            "himg": "https://images.fotmob.com/image_resources/logo/teamlogo/8121_small.png",
            "aimg": "https://images.fotmob.com/image_resources/logo/teamlogo/8639_small.png",
            "teams" : "Angers Vs Lille",
            "hteam" : "Angers",
            "ateam" : "Lille",
            "hotmat":"no",
            "link":[
  {
                    "type": "SD",
                "livelink":"https://651e411010b7d90167dfb5b08bc317d5.livehwc3.cn/pull.juqihuo.com/live/stream-3045619_lsd.m3u8?auth_key=1680981285-0-0-5235afd157c781a1b03e7ac542501776&user_session_id=041d42056ff7fe2846cab1dde0820c6a&edge_slice=true&sub_m3u8=true"
         
                },                     
{
                    "type": "SD 2",
                "livelink":"https://651e411010b7d90167dfb5b08bc317d5.livehwc3.cn/pull.juqihuo.com/live/stream-3045619_lsd.m3u8?auth_key=1680981285-0-0-5235afd157c781a1b03e7ac542501776&user_session_id=041d42056ff7fe2846cab1dde0820c6a&edge_slice=true&sub_m3u8=true"
         
                },
{
                    "type": "HD",
                "livelink":"https://sports01.livnvess.com/live/stream-115447.m3u8?txSecret=4ccfd2cce09ebba1d40b8fb546edbab7&txTime=6431b755"
         
                },
{
                    "type": "HD 2",
                "livelink":"https://651e411010b7d90167dfb5b08bc317d5.livehwc3.cn/pull.juqihuo.com/live/stream-3045619_lhd.m3u8?user_session_id=0ee3485de1482c388a86452c5e80d008&auth_key=1680981285-0-0-4f5f88c82d83413c66854177941881bb&edge_slice=true&sub_m3u8=true"
                }
                
            ]
},
{
           "league": "🏆 Premier League",
            "date": "April 8",
            "time": "live",
            "himg": "https://images.fotmob.com/image_resources/logo/teamlogo/8466_small.png",
            "aimg": "https://images.fotmob.com/image_resources/logo/teamlogo/8456_small.png",
            "teams" : "Southampton Vs Man City",
            "hteam" : "Southampton",
            "ateam" : "Man City",
            "hotmat":"yes",
            "link":[
  {
                    "type": "SD",
                "livelink":"https://7992be6d488db9d33fd803b87f5537aa.livehwc3.cn/pull06.scstream.net/live/stream-168740_lsd.m3u8?auth_key=1680979677-0-0-7345c8451985f5d5ef27128a76d3ddbc&edge_slice=true&sub_m3u8=true&user_session_id=a9a91314b062cf6f81fc8c5fedcb711f"
         
                },                     
{
                    "type": "SD 2",
                "livelink":"https://651e411010b7d90167dfb5b08bc317d5.livehwc3.cn/pull.juqihuo.com/live/stream-551866_lsd.m3u8?sub_m3u8=true&auth_key=1680981225-0-0-f3d9d17c1739a52b449333a551663072&edge_slice=true&user_session_id=b53dca2f59722de4095544b6c4a30377"
         
                },
{
                    "type": "HD",
                "livelink":"https://7992be6d488db9d33fd803b87f5537aa.livehwc3.cn/pull06.scstream.net/live/stream-168740_lsd.m3u8?sub_m3u8=true&edge_slice=true&auth_key=1680979677-0-0-7345c8451985f5d5ef27128a76d3ddbc&user_session_id=c1fe032ee7c8f16bcae3012d861d0a63"
         
                },
{
                    "type": "HD 2",
                "livelink":"https://651e411010b7d90167dfb5b08bc317d5.livehwc3.cn/pull.juqihuo.com/live/stream-551866_lhd.m3u8?sub_m3u8=true&user_session_id=42db90c607d1b10b1a9600321d071436&edge_slice=true&auth_key=1680981225-0-0-5b2077c2b802a6c6306af9b5a8e0eaad"
                },
{
                    "type": "FHD",
                "livelink":"https://pulldg.hongdel.top/live/hd-en-1-3747091.m3u8?auth_key=1680987910-0-0-2e37f4002d179868cc46c6dbf82f521a"
                }                
            ]
},
{
           "league": "🏆 Serie A",
            "date": "April 8",
            "time": "live",
            "himg": "https://images.fotmob.com/image_resources/logo/teamlogo/9804_small.png",
            "aimg": "https://images.fotmob.com/image_resources/logo/teamlogo/8686_small.png",
            "teams" : "Torino Vs Roma",
            "hteam" : "Torino",
            "ateam" : "Roma",
            "hotmat":"yes",
            "link":[
  {
                    "type": "SD",
                "livelink":"https://651e411010b7d90167dfb5b08bc317d5.livehwc3.cn/pull.juqihuo.com/live/stream-789220_lhd.m3u8?user_session_id=3690b22431d61a5189b0e9c2f33aba00&auth_key=1680981165-0-0-298d44938d08cd4693303e39ea5f3093&sub_m3u8=true&edge_slice=true"
         
                },                     
{
                    "type": "SD 2",
                "livelink":"https://651e411010b7d90167dfb5b08bc317d5.livehwc3.cn/pull.juqihuo.com/live/stream-789220_lhd.m3u8?user_session_id=147aa67674efac614c3ce2828e1f4098&edge_slice=true&sub_m3u8=true&auth_key=1680981105-0-0-dba80f77353608893ee48897d574b768"
         
                },
{
                    "type": "HD",
                "livelink":"https://sports01.livnvess.com/live/stream-214855.m3u8?txSecret=7d438ea155e4972e976724423298099a&txTime=6431b755"
         
                },
{
                    "type": "HD 2",
                "livelink":"https://sports01.livnvess.com/live/stream-113906.m3u8?txSecret=832996f2eff15d785840622e3e7d16b7&txTime=6431b755"
                }
                
            ]
},
{
           "league": "🏆 Laliga",
            "date": "April 8",
            "time": "live",
            "himg": "https://images.fotmob.com/image_resources/logo/teamlogo/8560_small.png",
            "aimg": "https://images.fotmob.com/image_resources/logo/teamlogo/8305_small.png",
            "teams" : "Real Sociedad Vs Getafe",
            "hteam" : "Real Sociedad",
            "ateam" : "Getafe",
            "hotmat":"no",
            "link":[
  
{
                    "type": "HD",
                "livelink":"https://sports01.livnvess.com/live/stream-192778.m3u8?txSecret=6e4f893db80236f73a16311c0b4f08c2&txTime=6431b794"
         
                },
{
                    "type": "HD 2",
                "livelink":"https://sports01.livnvess.com/live/stream-187579.m3u8?txSecret=13154da40cf501acb5ac7ffd587096fc&txTime=6431b794"
                }
                
            ]
},
{
           "league": "🏆 Serie A",
            "date": "April 8",
            "time": "live",
            "himg": "https://images.fotmob.com/image_resources/logo/teamlogo/9876_small.png",
            "aimg": "https://images.fotmob.com/image_resources/logo/teamlogo/7943_small.png",
            "teams" : "Hellas Verona Vs Sassuolo",
            "hteam" : "Hellas Verona",
            "ateam" : "Sassuolo",
            "hotmat":"no",
            "link":[
  {
                    
                    "type": "SD 2",
                "livelink":"https://651e411010b7d90167dfb5b08bc317d5.livehwc3.cn/pull.juqihuo.com/live/stream-466384_lsd.m3u8?sub_m3u8=true&user_session_id=00fd4dda0e2bfa7c4d0c3cd365facacd&auth_key=1680981045-0-0-21eed100c93692aea3be6f24e52cca5d&edge_slice=true"
         
                },

{
                    "type": "HD 2",
                "livelink":"https://651e411010b7d90167dfb5b08bc317d5.livehwc3.cn/pull.juqihuo.com/live/stream-466384_lhd.m3u8?sub_m3u8=true&edge_slice=true&auth_key=1680981045-0-0-f3d47c694073a742a2acdec328abef59&user_session_id=6a0d2e192dd134d66633d6003089a40c"
                }
                
            ]
},
{
           "league": "🏆 Bundesliga",
            "date": "April 8",
            "time": "live",
            "himg": "https://images.fotmob.com/image_resources/logo/teamlogo/8177_small.png",
            "aimg": "https://images.fotmob.com/image_resources/logo/teamlogo/178475_small.png",
            "teams" : "Hertha BSC Vs RB Leipzig",
            "hteam" : "Hertha BSC",
            "ateam" : "RB Leipzig",
            "hotmat":"no",
            "link":[
  {
                    "type": "SD",
                "livelink":"https://7992be6d488db9d33fd803b87f5537aa.livehwc3.cn/pull06.scstream.net/live/stream-118206_lsd.m3u8?auth_key=1680991677-0-0-ed31246cbaab5f266b8351e28bf5f136&sub_m3u8=true&edge_slice=true&user_session_id=ab8df68217f2260f53d441f20982c3ac"
         
                },                     
{
                    "type": "SD 2",
                "livelink":"https://651e411010b7d90167dfb5b08bc317d5.livehwc3.cn/pull.juqihuo.com/live/stream-459976_lsd.m3u8?auth_key=1680980985-0-0-7a2a682b5756d53604b863ebdd57e19f&user_session_id=6060c348e37486c9950278994a7576e7&sub_m3u8=true&edge_slice=true"
         
                },
{
                    "type": "HD",
                "livelink":"https://7992be6d488db9d33fd803b87f5537aa.livehwc3.cn/pull06.scstream.net/live/stream-118206_lhd.m3u8?edge_slice=true&sub_m3u8=true&user_session_id=bd45979fd74e0065c5b518db3f8aff1d&auth_key=1680991617-0-0-c3a52b5551524b3a03e83aed43caf4b4"
         
                },
{
                    "type": "HD 2",
                "livelink":"https://651e411010b7d90167dfb5b08bc317d5.livehwc3.cn/pull.juqihuo.com/live/stream-459976_lhd.m3u8?sub_m3u8=true&user_session_id=7daefa4ece5f1a1285c8f8f58228fb52&edge_slice=true&auth_key=1680980985-0-0-e7a6d46f8177a1865b010bb761b42f9c"
                }
                
            ]
},
{
           "league": "🏆 Serie A",
            "date": "April 9",
            "time": "live",
            "himg": "https://images.fotmob.com/image_resources/logo/teamlogo/8543_small.png",
            "aimg": "https://images.fotmob.com/image_resources/logo/teamlogo/9885_small.png",
            "teams" : "Lazio Vs Juventus",
            "hteam" : "Lazio",
            "ateam" : "Juventus",
            "hotmat":"no",
            "link":[
  {
                    "type": "SD",
                "livelink":"https://7992be6d488db9d33fd803b87f5537aa.livehwc3.cn/pull06.scstream.net/live/stream-161243_lsd.m3u8?edge_slice=true&auth_key=1680991917-0-0-da25c94cb65568c7db10061deb10035f&user_session_id=f67772c17488d8a75c6f7a7e2043f998&sub_m3u8=true"
         
                },                     
{
                    "type": "SD 2",
                "livelink":"https://651e411010b7d90167dfb5b08bc317d5.livehwc3.cn/pull.juqihuo.com/live/stream-459976_lsd.m3u8?edge_slice=true&auth_key=1680980985-0-0-7a2a682b5756d53604b863ebdd57e19f&sub_m3u8=true&user_session_id=40d7a0bc99f44d980a7696480087976f"
         
                },
{
                    "type": "HD",
                "livelink":"https://7992be6d488db9d33fd803b87f5537aa.livehwc3.cn/pull06.scstream.net/live/stream-161243_lhd.m3u8?auth_key=1680991917-0-0-bf91b053b353fec7f8f24910db396dde&sub_m3u8=true&user_session_id=7684de509662c0db5841826c6f444f1a&edge_slice=true"
         
                },
{
                    "type": "HD 2",
                "livelink":"https://651e411010b7d90167dfb5b08bc317d5.livehwc3.cn/pull.juqihuo.com/live/stream-459976_lhd.m3u8?auth_key=1680980985-0-0-e7a6d46f8177a1865b010bb761b42f9c&user_session_id=a8e273bd9588d4aad8d30f0387864f7a&edge_slice=true&sub_m3u8=true"
                }
                
            ]
},
{
           "league": "🏆 Laliga",
            "date": "April 9",
            "time": "live",
            "himg": "https://images.fotmob.com/image_resources/logo/teamlogo/8633_small.png",
            "aimg": "https://images.fotmob.com/image_resources/logo/teamlogo/10205_small.png",
            "teams" : "Real Madrid Vs Villarreal",
            "hteam" : "Real Madrid",
            "ateam" : "Villarreal",
            "hotmat":"yes",
            "link":[
  {
                    "type": "SD",
                "livelink":"https://7992be6d488db9d33fd803b87f5537aa.livehwc3.cn/pull06.scstream.net/live/stream-187579_lsd.m3u8?sub_m3u8=true&user_session_id=6fa5af71ade00af39368214726e0f2b6&auth_key=1680991857-0-0-5ff11e08c0aa3399986852f15a8fc4d7&edge_slice=true"
         
                },                     
{
                    "type": "SD 2",
                "livelink":"https://651e411010b7d90167dfb5b08bc317d5.livehwc3.cn/pull.juqihuo.com/live/stream-2376781_lsd.m3u8?sub_m3u8=true&user_session_id=25150acfbacfebb2bf119ce770b822f2&auth_key=1680980925-0-0-02f8e34fe94f8cc2d94e3a1069b44c8c&edge_slice=true"
         
                },
{
                    "type": "HD",
                "livelink":"https://sports01.livnvess.com/live/stream-115493.m3u8?txSecret=52e298027b1e2b43fa25703dbb865c3f&txTime=6431e671"
         
                },
{
                    "type": "HD 2",
                "livelink":"https://651e411010b7d90167dfb5b08bc317d5.livehwc3.cn/pull.juqihuo.com/live/stream-2376781_lhd.m3u8?sub_m3u8=true&user_session_id=7a2c535234ff7ace6ef98fa7c43d884a&auth_key=1680980925-0-0-44b14930ea64770e5416c29ea39e43c3&edge_slice=true"
                }
                
            ]
},
{
           "league": "🏆 Ligue 1",
            "date": "April 9",
            "time": "live",
            "himg": "https://images.fotmob.com/image_resources/logo/teamlogo/9831_small.png",
            "aimg": "https://images.fotmob.com/image_resources/logo/teamlogo/9847_small.png",
            "teams" : "Nice Vs PSG",
            "hteam" : "Mice",
            "ateam" : "PSG",
            "hotmat":"yes",
            "link":[
  {
                    "type": "SD",
                "livelink":"https://7992be6d488db9d33fd803b87f5537aa.livehwc3.cn/pull06.scstream.net/live/stream-121256_lsd.m3u8?auth_key=1680991797-0-0-c7eef7516fdca70bcf3f24dd97f9a78f&sub_m3u8=true&edge_slice=true&user_session_id=5615aeca865bd98b2669875088a1e26b"
         
                },                     
{
                    "type": "SD 2",
                "livelink":"https://651e411010b7d90167dfb5b08bc317d5.livehwc3.cn/pull.juqihuo.com/live/stream-362789_lsd.m3u8?auth_key=1680980865-0-0-b31b68651d255a1035f54ec4664c24fa&user_session_id=d816ac0abe88d82b7b5c21eda441c92d&sub_m3u8=true&edge_slice=true"
         
                },
{
                    "type": "HD",
                "livelink":"https://7992be6d488db9d33fd803b87f5537aa.livehwc3.cn/pull06.scstream.net/live/stream-121256_lhd.m3u8?auth_key=1680991797-0-0-d7d150e06bf1377472bc4db71a89285e&edge_slice=true&user_session_id=914270837f64c0e1a920cb8059a9f655&sub_m3u8=true"
         
                },
{
                    "type": "HD 2",
                "livelink":"https://651e411010b7d90167dfb5b08bc317d5.livehwc3.cn/pull.juqihuo.com/live/stream-362789_lhd.m3u8?user_session_id=e2bd654202ce19aa0f52b38b76db5127&auth_key=1680980865-0-0-fb4745108d9b0e768768bc73a0fbf873&sub_m3u8=true&edge_slice=true"
                }
                
            ]
}

          
]
