[   
{
           "league": "MAN U",
            "date": "TV Channel",
            "time": "live",
            "himg": "https://encrypted-tbn0.gstatic.com/images?q=tbn:ANd9GcSKh12j2lT6NtteO_RalxDNMemct8o1KxyGgr61rGYxZ2PJvl3x7h6XaCA&s=10",
            "aimg": "https://encrypted-tbn0.gstatic.com/images?q=tbn:ANd9GcSKh12j2lT6NtteO_RalxDNMemct8o1KxyGgr61rGYxZ2PJvl3x7h6XaCA&s=10",
            "teams" : "Man United TV",
            "hteam" : "MAN U",
            "ateam" : "TV",
            "hotmat":"yes",
            "link":[
                
{
                    "type": "MUTV 360 SD",
                "livelink":"https://bcovlive-a.akamaihd.net/r2d2c4ca5bf57456fb1d16255c1a535c8/eu-west-1/eu-west-1/6058004203001/profile_2/chunklist.m3u8"
         
                },
                
{
                    "type": "MUTV 240 SD",
                "livelink":"https://bcovlive-a.akamaihd.net/r2d2c4ca5bf57456fb1d16255c1a535c8/eu-west-1/eu-west-1/6058004203001/profile_3/chunklist.m3u8"
         
                },
{
                    "type": "MUTV 540 HD",
                "livelink":"https://bcovlive-a.akamaihd.net/r2d2c4ca5bf57456fb1d16255c1a535c8/eu-west-1/eu-west-1/6058004203001/profile_1/chunklist.m3u8"
         
                },
{
                    "type": "MAN U TV 1080HD",
                "livelink":"https://bcovlive-a.akamaihd.net/r2d2c4ca5bf57456fb1d16255c1a535c8/eu-west-1/eu-west-1/6058004203001/profile_1/chunklist.m3u8"
                }
                
            ]
},
{
           "league": "🏆 DFB Pokal Quarter Final",
            "date": "April 4",
            "time": "live",
            "himg": "https://images.fotmob.com/image_resources/logo/teamlogo/9810_small.png",
            "aimg": "https://images.fotmob.com/image_resources/logo/teamlogo/8149_small.png",
            "teams" : "Frankfurt Vs Union Berlin",
            "hteam" : "Frankfurt",
            "ateam" : "Union Berlin",
            "hotmat":"no",
            "link":[
  {
                    "type": "SD",
                "livelink":"https://7992be6d488db9d33fd803b87f5537aa.livehwc3.cn/pull06.scstream.net/live/stream-123226_lsd.m3u8?auth_key=1680645236-0-0-4d1b43ed588b30bcbaea0e1ecb6c497c&sub_m3u8=true&user_session_id=f23ef79a8c9eed53d91ea3fe287f8394&edge_slice=true"
         
                },                     
{
                    "type": "SD 2",
                "livelink":"https://651e411010b7d90167dfb5b08bc317d5.livehwc3.cn/pull.juqihuo.com/live/stream-551899_lsd.m3u8?auth_key=1680645284-0-0-60083555904b60c264dfc48a13a5a999&edge_slice=true&user_session_id=cacf77612a97a7d9abf77738155fa219&sub_m3u8=true"
         
                },
{
                    "type": "HD",
                "livelink":"https://7992be6d488db9d33fd803b87f5537aa.livehwc3.cn/pull06.scstream.net/live/stream-123226_lhd.m3u8?sub_m3u8=true&edge_slice=true&user_session_id=09718a3b098c7c605e70d78add627b05&auth_key=1680645236-0-0-9df5363b0952fee4040a94c6bf0a80b4"
         
                },
{
                    "type": "HD 2",
                "livelink":"https://651e411010b7d90167dfb5b08bc317d5.livehwc3.cn/pull.juqihuo.com/live/stream-551899_lhd.m3u8?auth_key=1680645284-0-0-e99113e49788b69140d4f03a7ffedef3&edge_slice=true&user_session_id=e7a085effad4abc007dedfbc93b8dd37&sub_m3u8=true"
                }
                
            ]
},
{
           "league": "🏆 Premier League",
            "date": "April 5",
            "time": "live",
            "himg": "https://images.fotmob.com/image_resources/logo/teamlogo/8197_small.png",
            "aimg": "https://images.fotmob.com/image_resources/logo/teamlogo/10252_small.png",
            "teams" : "Leicester City Vs Aston Villa",
            "hteam" : "Leicester City",
            "ateam" : "Aston Villa",
            "hotmat":"no",
            "link":[
  {
                    "type": "SD",
                "livelink":"https://yypull.gdsth.com/live/stream-2961234_ld.m3u8?auth_key=1680648884-0-0-a7bcee3b6d37b27fac23fe2a8279e947"
         
                },                     
{
                    "type": "SD 2",
                "livelink":"https://e53dc1c060e87be95abb5a524b1752f1.livehwc3.cn/pull06.scstream.net/live/stream-187579_lsd.m3u8?sub_m3u8=true&auth_key=1680649196-0-0-127712e14bcb520ea53252c63cf7d8aa&edge_slice=true&user_session_id=11804e4fb93e30f924f8588c7dc08c4d"
         
                },
{
                    "type": "HD",
                "livelink":"https://e53dc1c060e87be95abb5a524b1752f1.livehwc3.cn/pull06.scstream.net/live/stream-187579_lhd.m3u8?sub_m3u8=true&auth_key=1680649196-0-0-9e563acfa3736c17b444013ff601eccf&user_session_id=0d34746039ca4c9462f64a7f7548f8f7&edge_slice=true"
         
                },
{
                    "type": "HD 2",
                "livelink":"https://yypull.gdsth.com/live/stream-2961234.m3u8?auth_key=1680648884-0-0-71fd63b0f00460068126ce721f4fb7ca"
                }
                
            ]
},
{
           "league": "🏆 Premier League",
            "date": "April 5",
            "time": "live",
            "himg": "https://images.fotmob.com/image_resources/logo/teamlogo/8678_small.png",
            "aimg": "https://images.fotmob.com/image_resources/logo/teamlogo/10204_small.png",
            "teams" : "Bournemouth Vs Brighton",
            "hteam" : "Bournemouth",
            "ateam" : "Brighton",
            "hotmat":"no",
            "link":[
  {
                    "type": "SD",
                "livelink":"https://sports01.livnvess.com/live/stream-158814.m3u8?txSecret=5fa60cecfe6c6c7d115fcf73458756d6&txTime=642cacdc"
         
                },                     
{
                    "type": "SD 2",
                "livelink":"https://sports01.livnvess.com/live/stream-158814.m3u8?txSecret=a06946303f8e2c29c9129fa81107b8fa&txTime=642cac64"
         
                },
{
                    "type": "HD",
                "livelink":"https://e53dc1c060e87be95abb5a524b1752f1.livehwc3.cn/pull06.scstream.net/live/stream-187579_lhd.m3u8?sub_m3u8=true&user_session_id=2c980c59f18db69b605cb7a76c2306c2&auth_key=1680649136-0-0-3ca69374bb355ffdbb08f744bff406aa&edge_slice=true"
         
                },
{
                    "type": "HD 2",
                "livelink":"https://e53dc1c060e87be95abb5a524b1752f1.livehwc3.cn/pull06.scstream.net/live/stream-187579_lhd.m3u8?sub_m3u8=true&user_session_id=2c980c59f18db69b605cb7a76c2306c2&auth_key=1680649136-0-0-3ca69374bb355ffdbb08f744bff406aa&edge_slice=true"
                }
                
            ]
},
{
           "league": "🏆 Premier League",
            "date": "April 5",
            "time": "live",
            "himg": "https://images.fotmob.com/image_resources/logo/teamlogo/8463_small.png",
            "aimg": "https://images.fotmob.com/image_resources/logo/teamlogo/10203_small.png",
            "teams" : "Leeds Vs Nottingham",
            "hteam" : "Leeds",
            "ateam" : "Nottingham",
            "hotmat":"no",
            "link":[
  {
                    "type": "SD",
                "livelink":https://e53dc1c060e87be95abb5a524b1752f1.livehwc3.cn/pull06.scstream.net/live/stream-105131_lsd.m3u8?sub_m3u8=true&user_session_id=900c95ce9f3940a852b36a58cd4d8676&edge_slice=true&auth_key=1680649616-0-0-31da1c921ba43442225ebbd8ad683d44""
         
                },                     
{
                    "type": "SD 2",
                "livelink":"https://0255aacae47ba4334f30564256a2a325.livehwc3.cn/pull.juqihuo.com/live/stream-789220_lsd.m3u8?user_session_id=1413999e4fda96f33ab6db63f37d4022&sub_m3u8=true&auth_key=1680648765-0-0-217cc2cab22c2795d585fa17e74d1a5d&edge_slice=true"
         
                },
{
                    "type": "HD",
                "livelink":"https://e53dc1c060e87be95abb5a524b1752f1.livehwc3.cn/pull06.scstream.net/live/stream-105131_lhd.m3u8?sub_m3u8=true&user_session_id=af83276d3a8612bea2f8309d457b0073&edge_slice=true&auth_key=1680649616-0-0-dc64403dc8bfcff41e664f2ee99bcf45"
         
                },
{
                    "type": "HD 2",
                "livelink":"https://0255aacae47ba4334f30564256a2a325.livehwc3.cn/pull.juqihuo.com/live/stream-789220_lhd.m3u8?edge_slice=true&user_session_id=4f68b3d71127a59e0d4969e9934ea7d4&auth_key=1680648765-0-0-debee39a6f495a50e5ce9494bd2a910d&sub_m3u8=true"
                }
                
            ]
},
{
           "league": "🏆 DFB Pokal Quarter Final",
            "date": "April 5",
            "time": "1:15 AM",
            "himg": "https://images.fotmob.com/image_resources/logo/teamlogo/9823_small.png",
            "aimg": "https://images.fotmob.com/image_resources/logo/teamlogo/8358_small.png",
            "teams" : "Bayern München Vs SC Freiburg",
            "hteam" : "Bayern München",
            "ateam" : "SC Freiburg",
            "hotmat":"no",
            "link":[
  {
                    "type": "SD",
                "livelink":"https://e53dc1c060e87be95abb5a524b1752f1.livehwc3.cn/pull06.scstream.net/live/stream-420171_lsd.m3u8?sub_m3u8=true&auth_key=1680649076-0-0-4c466eb7beee822e6864dd8e33ef348a&user_session_id=c225547386a659b9af5514ea530fb29e&edge_slice=true"
         
                },                     
{
                    "type": "SD 2",
                "livelink":"https://yypull.gdsth.com/live/stream-112366_ld.m3u8?auth_key=1680648704-0-0-fd8ececd9eda12ab13db3b280cf3c733"
         
                },
{
                    "type": "HD",
                "livelink":"https://sports01.livnvess.com/live/stream-190631.m3u8?txSecret=be047c5ae51ec530cf6510be0b6fa11c&txTime=642caafc"
         
                },
{
                    "type": "HD 2",
                "livelink":"https://yypull.gdsth.com/live/stream-112366.m3u8?auth_key=1680648704-0-0-34bd7c9a1b63d1db656a2e1798878e94"
                }
                
            ]
},
{
           "league": "🏆 Premier League",
            "date": "April 5",
            "time": "live",
            "himg": "https://images.fotmob.com/image_resources/logo/teamlogo/8455_small.png",
            "aimg": "https://images.fotmob.com/image_resources/logo/teamlogo/8650_small.png",
            "teams" : "Chelsea Vs Liverpool",
            "hteam" : "Chelsea",
            "ateam" : "Liverpool",
            "hotmat":"yes",
            "link":[
  {
                    "type": "SD",
                "livelink":"https://e53dc1c060e87be95abb5a524b1752f1.livehwc3.cn/pull06.scstream.net/live/stream-147801_lsd.m3u8?sub_m3u8=true&user_session_id=1fd5ac8fa3e39c48a352631c77e959c4&edge_slice=true&auth_key=1680649556-0-0-64a5077f2929ea22c70ee96928cde11c"
         
                },                     
{
                    "type": "SD 2",
                "livelink":"https://0255aacae47ba4334f30564256a2a325.livehwc3.cn/pull.juqihuo.com/live/stream-551899_lsd.m3u8?edge_slice=true&auth_key=1680648644-0-0-fa6493e30f00577e02f158c124bf6dbe&user_session_id=08a433939fd1fdd6ad4cffb3e8efd605&sub_m3u8=true"
         
                },
{
                    "type": "HD",
                "livelink":"https://e53dc1c060e87be95abb5a524b1752f1.livehwc3.cn/pull06.scstream.net/live/stream-147801_lhd.m3u8?sub_m3u8=true&user_session_id=00a7b01ce7272065e37777719c3347e5&edge_slice=true&auth_key=1680649556-0-0-2d624916e23239d8147cc07061bd4772"
         
                },
{
                    "type": "HD 2",
                "livelink":"https://0255aacae47ba4334f30564256a2a325.livehwc3.cn/pull.juqihuo.com/live/stream-551899_lhd.m3u8?edge_slice=true&auth_key=1680648644-0-0-d5f85e24c20e907cecf80d76cfa3eb21&user_session_id=536b8f84e21f640f978b5f62f7068adb&sub_m3u8=true"
                }
                
            ]
},
{
           "league": "🏆 Copa del Rey Semi Final",
            "date": "April 5",
            "time": "1:30 AM",
            "himg": "https://images.fotmob.com/image_resources/logo/teamlogo/9885_small.png",
            "aimg": "https://images.fotmob.com/image_resources/logo/teamlogo/8636_small.png",
            "teams" : "Juventus Vs Inter",
            "hteam" : "Juventus",
            "ateam" : "Inter",
            "hotmat":"yes",
            "link":[
  {
                    "type": "SD",
                "livelink":""
         
                },                     
{
                    "type": "SD 2",
                "livelink":""
         
                },
{
                    "type": "HD",
                "livelink":""
         
                },
{
                    "type": "HD 2",
                "livelink":""
                }
                
            ]
},
{
           "league": "🏆 Copa del Rey Semi Final",
            "date": "April 5",
            "time": "1:30 AM",
            "himg": "https://images.fotmob.com/image_resources/logo/teamlogo/8315_small.png",
            "aimg": "https://images.fotmob.com/image_resources/logo/teamlogo/8371_small.png",
            "teams" : "Athletic Club Vs Osasuna",
            "hteam" : "Athletic Club",
            "ateam" : "Osasuna",
            "hotmat":"no",
            "link":[
  {
                    "type": "SD",
                "livelink":""
         
                },                     
{
                    "type": "SD 2",
                "livelink":""
         
                },
{
                    "type": "HD",
                "livelink":""
         
                },
{
                    "type": "HD 2",
                "livelink":""
                }
                
            ]
},
{
           "league": "🏆 Saudi Premier League",
            "date": "April 5",
            "time": "1:30 AM",
            "himg": "https://images.fotmob.com/image_resources/logo/teamlogo/582816_small.png",
            "aimg": "https://images.fotmob.com/image_resources/logo/teamlogo/101918_small.png",
            "teams" : "Al-Adalah Vs Al Nassr FC",
            "hteam" : "Al-Adalah",
            "ateam" : "Al Nassr FC",
            "hotmat":"yes",
            "link":[
  {
                    "type": "SD",
                "livelink":""
         
                },                     
{
                    "type": "SD 2",
                "livelink":""
         
                },
{
                    "type": "HD",
                "livelink":""
         
                },
{
                    "type": "HD 2",
                "livelink":""
                }
                
            ]
}

]
